dspackage/__init__.py
dspackage/masking.py
dspackage/tokenizers.py
dspackage/transformer.py
dspackage/Agents/rag.py
dspackage/ExpressNet/layers.py
dspackage/ExpressNet/model.py
dspackage-0.2.1.dist-info/METADATA
dspackage-0.2.1.dist-info/WHEEL
dspackage-0.2.1.dist-info/top_level.txt
dspackage-0.2.1.dist-info/RECORD
